csv_logger/__init__.py
csv_logger/csv_logger.py
csv_logger-1.3.0.dist-info/LICENSE
csv_logger-1.3.0.dist-info/METADATA
csv_logger-1.3.0.dist-info/WHEEL
csv_logger-1.3.0.dist-info/top_level.txt
csv_logger-1.3.0.dist-info/RECORD
