Metadata-Version: 2.1
Name: csv-logger
Version: 1.3.0
Summary: Simple class to log to csv using the logging rotating handler, output is a rolling csv log
Home-page: https://github.com/Morrious/csv-logger
Author: James Morris
Author-email: jemorris55@gmail.com
License: UNKNOWN
Project-URL: Bug Tracker, https://github.com/Morrious/csv-logger/issues
Platform: UNKNOWN
Classifier: Programming Language :: Python :: 3
Classifier: License :: OSI Approved :: MIT License
Classifier: Operating System :: OS Independent
Requires-Python: >=3.6
License-File: LICENSE
